mmw/__init__.py
mmw/animation.py
mmw/bind.py
mmw/consts.py
mmw/decoding.py
mmw/drawable.py
mmw/errors.py
mmw/figlet.py
mmw/formattedstring.py
mmw/formatting.py
mmw/graphic.py
mmw/menu.py
mmw/progressbar.py
mmw/screen.py
mmw/screen_options.py
mmw/styles.py
mmw/textfield.py
mmw/window.py
mmw-1.1.dist-info/DESCRIPTION.rst
mmw-1.1.dist-info/METADATA
mmw-1.1.dist-info/RECORD
mmw-1.1.dist-info/WHEEL
mmw-1.1.dist-info/metadata.json
mmw-1.1.dist-info/top_level.txt
