Metadata-Version: 2.0
Name: mmw
Version: 1.1
Summary: This is a library for displaying curses-like windows
Home-page: https://github.com/Mm2PL/mmw
Author: Maciej Marciniak
Author-email: jakis128@gmail.com
License: GPL-3
Platform: UNKNOWN
Classifier: Intended Audience :: Developers
Classifier: Development Status :: 5 - Production/Stable
Classifier: Programming Language :: Python :: 3.6
Classifier: Environment :: Console
Classifier: License :: OSI Approved :: GNU General Public License v3 (GPLv3)
Classifier: Operating System :: OS Independent
Classifier: Topic :: Software Development :: Libraries
Requires-Python: >=3
